day9/memory.v
// Memory RTL Code
module memory (addr,cs,re,we,clk,reset,data_in,data_out);
parameter addr_width=16;  parameter data_width=32;
input [addr_width-1:0] addr;
input cs;   input re,we;
input clk,reset;
input [data_width-1:0] data_in; 
output [data_width-1:0] data_out;

reg [data_width-1:0] data_out;
reg [data_width-1:0]  mem [0:2**addr_width];
integer i;

always@(posedge clk)
begin: MEM
  if(reset)    begin
          mem[addr]<=0;
  end   else    begin
   if(cs)     begin
       if(we)         begin
           mem[addr]  <=data_in;
        end
       if(re)  begin
           data_out <=mem[addr]; 
       end
      end
    end
end
endmodule

day9/memory_tb.v
// Memory Test bench code
module memory_tb(); 
  parameter addr_width=16;
  parameter data_width=32; 
  integer count;
  reg cs,clk,reset,re,we;
  reg [addr_width-1:0] addr;
  reg [data_width-1:0] data_in;
  wire [data_width-1:0] data_out;

// memory instance
 memory #(addr_width, data_width) memory_inst(addr,cs,re,we,clk,reset,data_in,data_out);
 
 initial begin
   clk=0;    reset=0;
#1 cs=0; 
#1 cs=1;
#1 cs=0;
#2 reset=1;
#2  reset=0;
 end
// clock generation
always #5 clk=~clk;
// calling write and read tasks
 initial begin
 for(count=0; count< 'h10;count=count+1)  begin  
      write_task(count);
      read_task(count);  
 end
 $finish; // end the test
end
// monitor the log
initial
   $monitor($time,"  addr=%hdata_in=%h,data_out=%h", addr, data_in,data_out);
   
   // dump the vcd 
initial begin
    $dumpfile("dump.vcd");
    $dumpvars;
end
// write task
task write_task;
input [addr_width-1:0] addr_in;
begin
 @(posedge clk);
  cs=1; we=1; re=0;        //data_in=$random;
  data_in=$random;
  addr=addr_in;
  @(posedge clk);
  we=0;
end
endtask

//read task
task read_task;
input [addr_width-1:0] addr_in;
begin
   @(posedge clk)
   cs=1; we=0;re=1;
   addr =addr_in;
   @(posedge clk)
   re = 0;


 end
endtask
endmodule

day9/dump.vcd
$date
    Jun 16, 2026  10:52:52
$end
$version
    TOOL:	ncsim(64)	15.20-s086
$end
$timescale
    1 ns
$end

$scope module memory_tb $end
$var parameter 32 !    addr_width  $end
$var parameter 32 "    data_width  $end
$var integer  32 #    count  $end
$var reg       1 $    cs  $end
$var reg       1 %    clk  $end
$var reg       1 &    reset  $end
$var reg       1 '    re  $end
$var reg       1 (    we  $end
$var reg      16 )    addr [15:0] $end
$var reg      32 *    data_in [31:0] $end
$var wire     32 +    data_out [31:0] $end

$scope module memory_inst $end
$var parameter 32 ,    addr_width  $end
$var parameter 32 -    data_width  $end
$var wire     16 .    addr [15:0] $end
$var wire      1 /    cs  $end
$var wire      1 0    re  $end
$var wire      1 1    we  $end
$var wire      1 2    clk  $end
$var wire      1 3    reset  $end
$var wire     32 4    data_in [31:0] $end
$var reg      32 5    data_out [31:0] $end
$var integer  32 6    i  $end
$upscope $end


$scope task write_task $end
$var reg      16 7    addr_in [15:0] $end
$upscope $end


$scope task read_task $end
$var reg      16 8    addr_in [15:0] $end
$upscope $end

$upscope $end

$enddefinitions $end
$dumpvars
b100000 -
b10000 ,
b100000 "
b10000 !
b0 #
x$
0%
0&
x'
x(
bx )
bx *
bx +
bx .
x/
x0
x1
02
03
bx 4
bx 5
bx 6
b0 7
bx 8
$end
#1
0$
0/
#2
1$
1/
#3
0$
0/
#5
1%
1&
1$
1(
0'
b10010000101010011010100100100 *
b0 )
b0 .
b10010000101010011010100100100 4
00
11
1/
13
12
#7
0&
03
#10
0%
02
#15
1%
0(
b0 8
01
12
#20
0%
02
#25
1%
1'
10
12
b0 5
b0 +
#30
0%
02
#35
1%
0'
b1 #
b1 7
00
12
#40
0%
02
#45
1%
1(
b11000000100010010101111010000001 *
b1 )
b1 .
b11000000100010010101111010000001 4
11
12
#50
0%
02
#55
1%
0(
b1 8
01
12
#60
0%
02
#65
1%
1'
10
12
b11000000100010010101111010000001 5
b11000000100010010101111010000001 +
#70
0%
02
#75
1%
0'
b10 #
b10 7
00
12
#80
0%
02
#85
1%
1(
b10000100100001001101011000001001 *
b10 )
b10 .
b10000100100001001101011000001001 4
11
12
#90
0%
02
#95
1%
0(
b10 8
01
12
#100
0%
02
#105
1%
1'
10
12
b10000100100001001101011000001001 5
b10000100100001001101011000001001 +
#110
0%
02
#115
1%
0'
b11 #
b11 7
00
12
#120
0%
02
#125
1%
1(
b10110001111100000101011001100011 *
b11 )
b11 .
b10110001111100000101011001100011 4
11
12
#130
0%
02
#135
1%
0(
b11 8
01
12
#140
0%
02
#145
1%
1'
10
12
b10110001111100000101011001100011 5
b10110001111100000101011001100011 +
#150
0%
02
#155
1%
0'
b100 #
b100 7
00
12
#160
0%
02
#165
1%
1(
b110101110010111101100001101 *
b100 )
b100 .
b110101110010111101100001101 4
11
12
#170
0%
02
#175
1%
0(
b100 8
01
12
#180
0%
02
#185
1%
1'
10
12
b110101110010111101100001101 5
b110101110010111101100001101 +
#190
0%
02
#195
1%
0'
b101 #
b101 7
00
12
#200
0%
02
#205
1%
1(
b1000110110111111001100110001101 *
b101 )
b101 .
b1000110110111111001100110001101 4
11
12
#210
0%
02
#215
1%
0(
b101 8
01
12
#220
0%
02
#225
1%
1'
10
12
b1000110110111111001100110001101 5
b1000110110111111001100110001101 +
#230
0%
02
#235
1%
0'
b110 #
b110 7
00
12
#240
0%
02
#245
1%
1(
b10110010110000101000010001100101 *
b110 )
b110 .
b10110010110000101000010001100101 4
11
12
#250
0%
02
#255
1%
0(
b110 8
01
12
#260
0%
02
#265
1%
1'
10
12
b10110010110000101000010001100101 5
b10110010110000101000010001100101 +
#270
0%
02
#275
1%
0'
b111 #
b111 7
00
12
#280
0%
02
#285
1%
1(
b10001001001101110101001000010010 *
b111 )
b111 .
b10001001001101110101001000010010 4
11
12
#290
0%
02
#295
1%
0(
b111 8
01
12
#300
0%
02
#305
1%
1'
10
12
b10001001001101110101001000010010 5
b10001001001101110101001000010010 +
#310
0%
02
#315
1%
0'
b1000 #
b1000 7
00
12
#320
0%
02
#325
1%
1(
b111100111110001100000001 *
b1000 )
b1000 .
b111100111110001100000001 4
11
12
#330
0%
02
#335
1%
0(
b1000 8
01
12
#340
0%
02
#345
1%
1'
10
12
b111100111110001100000001 5
b111100111110001100000001 +
#350
0%
02
#355
1%
0'
b1001 #
b1001 7
00
12
#360
0%
02
#365
1%
1(
b110110101111100110100001101 *
b1001 )
b1001 .
b110110101111100110100001101 4
11
12
#370
0%
02
#375
1%
0(
b1001 8
01
12
#380
0%
02
#385
1%
1'
10
12
b110110101111100110100001101 5
b110110101111100110100001101 +
#390
0%
02
#395
1%
0'
b1010 #
b1010 7
00
12
#400
0%
02
#405
1%
1(
b111011001000111111000101110110 *
b1010 )
b1010 .
b111011001000111111000101110110 4
11
12
#410
0%
02
#415
1%
0(
b1010 8
01
12
#420
0%
02
#425
1%
1'
10
12
b111011001000111111000101110110 5
b111011001000111111000101110110 +
#430
0%
02
#435
1%
0'
b1011 #
b1011 7
00
12
#440
0%
02
#445
1%
1(
b11110100011011100110100111101 *
b1011 )
b1011 .
b11110100011011100110100111101 4
11
12
#450
0%
02
#455
1%
0(
b1011 8
01
12
#460
0%
02
#465
1%
1'
10
12
b11110100011011100110100111101 5
b11110100011011100110100111101 +
#470
0%
02
#475
1%
0'
b1100 #
b1100 7
00
12
#480
0%
02
#485
1%
1(
b1110110110101000101011111101101 *
b1100 )
b1100 .
b1110110110101000101011111101101 4
11
12
#490
0%
02
#495
1%
0(
b1100 8
01
12
#500
0%
02
#505
1%
1'
10
12
b1110110110101000101011111101101 5
b1110110110101000101011111101101 +
#510
0%
02
#515
1%
0'
b1101 #
b1101 7
00
12
#520
0%
02
#525
1%
1(
b1000110001011011111011110001100 *
b1101 )
b1101 .
b1000110001011011111011110001100 4
11
12
#530
0%
02
#535
1%
0(
b1101 8
01
12
#540
0%
02
#545
1%
1'
10
12
b1000110001011011111011110001100 5
b1000110001011011111011110001100 +
#550
0%
02
#555
1%
0'
b1110 #
b1110 7
00
12
#560
0%
02
#565
1%
1(
b1111100111111011110100111111001 *
b1110 )
b1110 .
b1111100111111011110100111111001 4
11
12
#570
0%
02
#575
1%
0(
b1110 8
01
12
#580
0%
02
#585
1%
1'
10
12
b1111100111111011110100111111001 5
b1111100111111011110100111111001 +
#590
0%
02
#595
1%
0'
b1111 #
b1111 7
00
12
#600
0%
02
#605
1%
1(
b11100011001101110010010011000110 *
b1111 )
b1111 .
b11100011001101110010010011000110 4
11
12
#610
0%
02
#615
1%
0(
b1111 8
01
12
#620
0%
02
#625
1%
1'
10
12
b11100011001101110010010011000110 5
b11100011001101110010010011000110 +
#630
0%
02
#635
1%
0'
b10000 #
