day22/fifo/synthesis/fifo.v
// Asynchronous memory with gray code pointer exchange
// 2^n depth supported

`default_nettype none
`timescale 1ps/1ps

module async_fifo #(
    parameter DSIZE = 8,
    parameter ASIZE = 4
) (
    input   wreq, wclk, wrst_n,
    input   rreq, rclk, rrst_n,
    input   [DSIZE-1:0] wdata,
    output  [DSIZE-1:0] rdata,
    output  reg wfull,
    output  reg rempty
);

reg     [ASIZE-1:0]   wq2_rptr, wq1_rptr, rptr;
reg     [ASIZE-1:0]   rq2_wptr, rq1_wptr, wptr;
wire    rempty_val;
wire    [ASIZE : 0] rptr_nxt;
wire    [ASIZE-1:0] raddr;
reg     [ASIZE:0] rbin;
wire    [ASIZE:0] rbin_nxt;
wire    [ASIZE-1:0] waddr;
reg     [ASIZE:0] wbin;
wire    [ASIZE:0] wbin_nxt;
wire    [ASIZE : 0] wptr_nxt;

// synchronizing rptr to wclk
always @(posedge wclk or negedge wrst_n) begin
    if(!wrst_n)
        {wq2_rptr, wq1_rptr} <= 8'b0;
    else
        {wq2_rptr, wq1_rptr} <= {wq1_rptr, rptr};
end

// synchronizing wptr to rclk
always @(posedge rclk or negedge rrst_n) begin
    if(!rrst_n)
        {rq2_wptr, rq1_wptr} <= 8'b0;
    else
        {rq2_wptr, rq1_wptr} <= {rq1_wptr, wptr};
end

// generating rempty condition
//reg     rempty;
assign  rempty_val = (rptr_nxt == rq2_wptr); 

always @(posedge rclk or negedge rrst_n) begin
    if(!rrst_n)
        rempty <= 1'b0;
    else
        rempty <= rempty_val;
end

// generating read address for fifomem
assign rbin_nxt = rbin + (rreq & ~rempty);

always @ (posedge rclk or negedge rrst_n) 
    if (!rrst_n)
        rbin <= 0;
    else 
        rbin <= rbin_nxt;
assign raddr = rbin[ASIZE-1:0]; 

// generating rptr to send to wclk domain
// convert from binary to gray
assign rptr_nxt = rbin_nxt ^ (rbin_nxt>>1);

always @ (posedge rclk or negedge rrst_n)
    if (!rrst_n)
        rptr <= 0;
    else 
        rptr <= rptr_nxt;

// generating write address for fifomem
assign wbin_nxt = wbin + (wreq & !wfull);

always @ (posedge wclk or negedge wrst_n)
    if(!wrst_n)
        wbin <= 0;
    else
        wbin <= wbin_nxt;

assign waddr = wbin [ASIZE-1:0];

// generating wptr to send to rclk domain
// convert from binary to gray
assign wptr_nxt = (wbin_nxt>>1) ^ wbin_nxt; 

always @ (posedge wclk or negedge wrst_n)
    if(!wrst_n)
        wptr <= 0;
    else
        wptr <= wptr_nxt;

// generate wfull condition
wire wfull_val;
assign wfull_val = (wq2_rptr == {~wptr[ASIZE-1 : ASIZE-2],wptr[ASIZE-2 : 0]});

always @ (posedge wclk or negedge wrst_n)
    if (!wrst_n)
        wfull <= 0;
    else 
        wfull <= wfull_val;

// fifomem
// Using Verilog memory model
localparam DEPTH = (1 << (ASIZE));
reg [DSIZE-1 : 0] mem [0: DEPTH -1];

assign rdata = mem[raddr];

always @ (posedge wclk)
    if (wreq & !wfull) mem[waddr] <= wdata;

endmodule

day22/fifo/synthesis/fifo_tb.v
// TB to verify async_fifo

`default_nettype none
`timescale 1ps/1ps

module async_fifo_tb ();

parameter DSIZE = 8;
parameter ASIZE = 4;
parameter WCLK_PERIOD = 10;
parameter RCLK_PERIOD = 40;

reg wreq, wclk, wrst_n, rreq, rclk, rrst_n;
reg [DSIZE-1:0] wdata;
wire [DSIZE-1:0] rdata;
wire wfull, rempty;

// Instance
async_fifo 
//#(     
 //   .DSIZE(DSIZE),
 //   .ASIZE(ASIZE)
//)
u_async_fifo
(
    .wreq (wreq), .wrst_n(wrst_n), .wclk(wclk),
    .rreq(rreq), .rclk(rclk), .rrst_n(rrst_n),
    .wdata(wdata), .rdata(rdata), .wfull(wfull), .rempty(rempty)
);

initial begin
    wrst_n = 0;
    wclk = 0;
    wreq = 0;
    wdata = 0;
    repeat (2) #(WCLK_PERIOD/2) wclk = ~wclk;
    wrst_n = 1;
    forever #(WCLK_PERIOD/2) wclk = ~wclk;
end

initial begin
    rrst_n = 0;
    rclk = 0;
    rreq = 0;
    repeat (2) #(RCLK_PERIOD/2) rclk = ~rclk;
    rrst_n = 1;
    forever  #(RCLK_PERIOD/2) rclk = ~rclk;
end

initial 
  begin
    $dumpfile("dump.vcd"); 
    $dumpvars;
end  


initial begin
    repeat (4) @ (posedge wclk);
     @(negedge wclk); wreq = 1;wdata = 8'd1;
     @(negedge wclk); wreq = 1;wdata = 8'd2;
     @(negedge wclk); wreq = 1;wdata = 8'd3;
     @(negedge wclk); wreq = 1;wdata = 8'd4;
     @(negedge wclk); wreq = 1;wdata = 8'd5;
     @(negedge wclk); wreq = 1;wdata = 8'd6;
     @(negedge wclk); wreq = 1;wdata = 8'd7;
     @(negedge wclk); wreq = 1;wdata = 8'd8;
     @(negedge wclk); wreq = 1;wdata = 8'd9;
     @(negedge wclk); wreq = 1;wdata = 8'd10;
     @(negedge wclk); wreq = 1;wdata = 8'd11;
     @(negedge wclk); wreq = 1;wdata = 8'd12;
     @(negedge wclk); wreq = 1;wdata = 8'd13;
     @(negedge wclk); wreq = 1;wdata = 8'd14;
     @(negedge wclk); wreq = 1;wdata = 8'd15;
     @(negedge wclk); wreq = 1;wdata = 8'd16;
     @(negedge wclk); wreq = 0;

     @(negedge rclk); rreq = 1;
     repeat (17) @(posedge rclk);
     rreq=0;

     #100;
     $finish;
end

endmodule

day22/fifo/synthesis/dump.vcd
$date
    Jul  1, 2026  13:10:21
$end
$version
    TOOL:	ncsim(64)	15.20-s086
$end
$timescale
    1 ps
$end

$scope module async_fifo_tb $end
$var parameter 32 !    DSIZE  $end
$var parameter 32 "    ASIZE  $end
$var parameter 32 #    WCLK_PERIOD  $end
$var parameter 32 $    RCLK_PERIOD  $end
$var reg       1 %    wreq  $end
$var reg       1 &    wclk  $end
$var reg       1 '    wrst_n  $end
$var reg       1 (    rreq  $end
$var reg       1 )    rclk  $end
$var reg       1 *    rrst_n  $end
$var reg       8 +    wdata [7:0] $end
$var wire      8 ,    rdata [7:0] $end
$var wire      1 -    wfull  $end
$var wire      1 .    rempty  $end

$scope module u_async_fifo $end
$var parameter 32 /    DSIZE  $end
$var parameter 32 0    ASIZE  $end
$var wire      1 1    wreq  $end
$var wire      1 2    wclk  $end
$var wire      1 3    wrst_n  $end
$var wire      1 4    rreq  $end
$var wire      1 5    rclk  $end
$var wire      1 6    rrst_n  $end
$var wire      8 7    wdata [7:0] $end
$var wire      8 ,    rdata [7:0] $end
$var reg       1 8    wfull  $end
$var reg       1 9    rempty  $end
$var reg       4 :    wq2_rptr [3:0] $end
$var reg       4 ;    wq1_rptr [3:0] $end
$var reg       4 <    rptr [3:0] $end
$var reg       4 =    rq2_wptr [3:0] $end
$var reg       4 >    rq1_wptr [3:0] $end
$var reg       4 ?    wptr [3:0] $end
$var wire      1 @    rempty_val  $end
$var wire      5 A    rptr_nxt [4:0] $end
$var wire      4 B    raddr [3:0] $end
$var reg       5 C    rbin [4:0] $end
$var wire      5 D    rbin_nxt [4:0] $end
$var wire      4 E    waddr [3:0] $end
$var reg       5 F    wbin [4:0] $end
$var wire      5 G    wbin_nxt [4:0] $end
$var wire      5 H    wptr_nxt [4:0] $end
$var wire      1 I    wfull_val  $end
$var parameter 32 J    DEPTH  $end
$upscope $end

$upscope $end

$enddefinitions $end
$dumpvars
b10000 J
b100 0
b1000 /
b101000 $
b1010 #
b100 "
b1000 !
0%
0&
0'
0(
0)
0*
b0 +
bx ,
0-
0.
01
02
03
04
05
06
b0 7
08
09
b0 :
b0 ;
b0 <
b0 =
b0 >
b0 ?
1@
b0 A
b0 B
b0 C
b0 D
b0 E
b0 F
b0 G
b0 H
0I
$end
#5
1&
12
#10
0&
1'
13
02
#15
1&
12
#20
1)
0&
02
15
#25
1&
12
#30
0&
02
#35
1&
12
#40
0)
1*
0&
1%
b1 +
b1 7
11
02
16
05
b1 G
b1 H
#45
1&
12
b1 F
b1 ?
b1 ,
b1 E
b10 G
b11 H
#50
0&
b10 +
b10 7
02
#55
1&
12
b10 F
b11 ?
b10 E
b11 G
b10 H
#60
1)
0&
b11 +
b11 7
02
15
19
b11 >
1.
#65
1&
12
b11 F
b10 ?
b11 E
b100 G
b110 H
#70
0&
b100 +
b100 7
02
#75
1&
12
b100 F
b110 ?
b100 E
b101 G
b111 H
#80
0)
0&
b101 +
b101 7
02
05
#85
1&
12
b101 F
b111 ?
b101 E
b110 G
b101 H
#90
0&
b110 +
b110 7
02
#95
1&
12
b110 F
b101 ?
b110 E
b111 G
b100 H
#100
1)
0&
b111 +
b111 7
02
15
b101 >
b11 =
0@
#105
1&
12
b111 F
b100 ?
b111 E
b1000 G
b1100 H
#110
0&
b1000 +
b1000 7
02
#115
1&
12
b1000 F
b1100 ?
b1000 E
b1001 G
b1101 H
#120
0)
0&
b1001 +
b1001 7
02
05
#125
1&
12
b1001 F
b1101 ?
b1001 E
b1010 G
b1111 H
#130
0&
b1010 +
b1010 7
02
#135
1&
12
b1010 F
b1111 ?
b1010 E
b1011 G
b1110 H
#140
1)
0&
b1011 +
b1011 7
02
15
09
b1111 >
b101 =
0.
#145
1&
12
b1011 F
b1110 ?
b1011 E
b1100 G
b1010 H
#150
0&
b1100 +
b1100 7
02
#155
1&
12
b1100 F
b1010 ?
b1100 E
b1101 G
b1011 H
#160
0)
0&
b1101 +
b1101 7
02
05
#165
1&
12
b1101 F
b1011 ?
b1101 E
b1110 G
b1001 H
#170
0&
b1110 +
b1110 7
02
#175
1&
12
b1110 F
b1001 ?
b1110 E
b1111 G
b1000 H
#180
1)
0&
b1111 +
b1111 7
02
15
b1001 >
b1111 =
#185
1&
12
b1111 F
b1000 ?
b1111 E
b10000 G
b11000 H
#190
0&
b10000 +
b10000 7
02
#195
1&
12
b10000 F
b0 E
b10001 G
b11001 H
#200
0)
0&
0%
01
02
05
b10000 G
b11000 H
#205
1&
12
#210
0&
02
#215
1&
12
#220
1)
0&
02
15
b1000 >
b1001 =
#225
1&
12
#230
0&
02
#235
1&
12
#240
0)
0&
1(
14
02
05
b1 D
b1 A
#245
1&
12
#250
0&
02
#255
1&
12
#260
1)
0&
02
15
b1 <
b1 C
b1000 =
b1 B
b10 D
b11 A
b10 ,
#265
1&
12
b1 ;
#270
0&
02
#275
1&
12
b1 :
#280
0)
0&
02
05
#285
1&
12
#290
0&
02
#295
1&
12
#300
1)
0&
02
15
b11 <
b10 C
b10 B
b11 D
b10 A
b11 ,
#305
1&
12
b11 ;
#310
0&
02
#315
1&
12
b11 :
#320
0)
0&
02
05
#325
1&
12
#330
0&
02
#335
1&
12
#340
1)
0&
02
15
b10 <
b11 C
b11 B
b100 D
b110 A
b100 ,
#345
1&
12
b10 ;
#350
0&
02
#355
1&
12
b10 :
#360
0)
0&
02
05
#365
1&
12
#370
0&
02
#375
1&
12
#380
1)
0&
02
15
b110 <
b100 C
b100 B
b101 D
b111 A
b101 ,
#385
1&
12
b110 ;
#390
0&
02
#395
1&
12
b110 :
#400
0)
0&
02
05
#405
1&
12
#410
0&
02
#415
1&
12
#420
1)
0&
02
15
b111 <
b101 C
b101 B
b110 D
b101 A
b110 ,
#425
1&
12
b111 ;
#430
0&
02
#435
1&
12
b111 :
#440
0)
0&
02
05
#445
1&
12
#450
0&
02
#455
1&
12
#460
1)
0&
02
15
b101 <
b110 C
b110 B
b111 D
b100 A
b111 ,
#465
1&
12
b101 ;
#470
0&
02
#475
1&
12
b101 :
#480
0)
0&
02
05
#485
1&
12
#490
0&
02
#495
1&
12
#500
1)
0&
02
15
b100 <
b111 C
b111 B
b1000 D
b1100 A
b1000 ,
#505
1&
12
b100 ;
#510
0&
02
#515
1&
12
b100 :
#520
0)
0&
02
05
#525
1&
12
#530
0&
02
#535
1&
12
#540
1)
0&
02
15
b1100 <
b1000 C
b1000 B
b1001 D
b1101 A
b1001 ,
#545
1&
12
b1100 ;
#550
0&
02
#555
1&
12
b1100 :
#560
0)
0&
02
05
#565
1&
12
#570
0&
02
#575
1&
12
#580
1)
0&
02
15
b1101 <
b1001 C
b1001 B
b1010 D
b1111 A
b1010 ,
#585
1&
12
b1101 ;
#590
0&
02
#595
1&
12
b1101 :
#600
0)
0&
02
05
#605
1&
12
#610
0&
02
#615
1&
12
#620
1)
0&
02
15
b1111 <
b1010 C
b1010 B
b1011 D
b1110 A
b1011 ,
#625
1&
12
b1111 ;
#630
0&
02
#635
1&
12
b1111 :
#640
0)
0&
02
05
#645
1&
12
#650
0&
02
#655
1&
12
#660
1)
0&
02
15
b1110 <
b1011 C
b1011 B
b1100 D
b1010 A
b1100 ,
#665
1&
12
b1110 ;
#670
0&
02
#675
1&
12
b1110 :
#680
0)
0&
02
05
#685
1&
12
#690
0&
02
#695
1&
12
#700
1)
0&
02
15
b1010 <
b1100 C
b1100 B
b1101 D
b1011 A
b1101 ,
#705
1&
12
b1010 ;
#710
0&
02
#715
1&
12
b1010 :
#720
0)
0&
02
05
#725
1&
12
#730
0&
02
#735
1&
12
#740
1)
0&
02
15
b1011 <
b1101 C
b1101 B
b1110 D
b1001 A
b1110 ,
#745
1&
12
b1011 ;
#750
0&
02
#755
1&
12
b1011 :
#760
0)
0&
02
05
#765
1&
12
#770
0&
02
#775
1&
12
#780
1)
0&
02
15
b1001 <
b1110 C
b1110 B
b1111 D
b1000 A
b1111 ,
1@
#785
1&
12
b1001 ;
#790
0&
02
#795
1&
12
b1001 :
#800
0)
0&
02
05
#805
1&
12
#810
0&
02
#815
1&
12
#820
1)
0&
02
15
b1000 <
19
b1111 C
b1111 B
1.
b10000 ,
#825
1&
12
b1000 ;
#830
0&
02
#835
1&
12
b1000 :
1I
#840
0)
0&
02
05
#845
1&
12
18
1-
#850
0&
02
#855
1&
12
#860
1)
0&
02
15
#865
1&
12
#870
0&
02
#875
1&
12
#880
0)
0&
02
05
#885
1&
12
#890
0&
02
#895
1&
12
#900
1)
0&
0(
04
02
15
